e2xgrader/__init__.py
e2xgrader/__main__.py
e2xgrader/__version__.py
e2xgrader/apps/__init__.py
e2xgrader/apps/activatemodeapp.py
e2xgrader/apps/baseapp.py
e2xgrader/apps/deactivatemodeapp.py
e2xgrader/apps/e2xgraderapp.py
e2xgrader/apps/showmodeapp.py
e2xgrader/apps/togglemodeapp.py
e2xgrader/config/__init__.py
e2xgrader/exchange/__init__.py
e2xgrader/exchange/collect.py
e2xgrader/exchange/exchange.py
e2xgrader/exchange/fetch_assignment.py
e2xgrader/exchange/fetch_feedback.py
e2xgrader/exchange/hash_utils.py
e2xgrader/exchange/list.py
e2xgrader/exchange/release_assignment.py
e2xgrader/exchange/release_feedback.py
e2xgrader/exchange/submit.py
e2xgrader/exchange/utils.py
e2xgrader/exporters/__init__.py
e2xgrader/exporters/exporter.py
e2xgrader/exporters/gradeexporter.py
e2xgrader/exporters/submissionexporter.py
e2xgrader/exporters/filters/__init__.py
e2xgrader/exporters/filters/highlight.py
e2xgrader/exporters/templates/hashcode_cell.html
e2xgrader/extensions/__init__.py
e2xgrader/extensions/base.py
e2xgrader/extensions/manager.py
e2xgrader/extensions/nbextensions.py
e2xgrader/extensions/serverextensions.py
e2xgrader/extensions/utils.py
e2xgrader/graders/__init__.py
e2xgrader/graders/base.py
e2xgrader/graders/code.py
e2xgrader/graders/multiplechoice.py
e2xgrader/graders/singlechoice.py
e2xgrader/preprocessors/__init__.py
e2xgrader/preprocessors/clearhiddentests.py
e2xgrader/preprocessors/clearsolutions.py
e2xgrader/preprocessors/extractattachments.py
e2xgrader/preprocessors/filtercellsbyid.py
e2xgrader/preprocessors/filtertests.py
e2xgrader/preprocessors/overwritecells.py
e2xgrader/preprocessors/permutetasks.py
e2xgrader/preprocessors/saveautogrades.py
e2xgrader/preprocessors/savecells.py
e2xgrader/preprocessors/scramble.py
e2xgrader/preprocessors/unpermutetasks.py
e2xgrader/preprocessors/unscramble.py
e2xgrader/preprocessors/validateextracells.py
e2xgrader/server_extensions/__init__.py
e2xgrader/server_extensions/apps/assignment_list/__init__.py
e2xgrader-0.3.3.dist-info/METADATA
e2xgrader-0.3.3.dist-info/WHEEL
e2xgrader-0.3.3.dist-info/entry_points.txt
e2xgrader-0.3.3.dist-info/licenses/LICENSE
e2xgrader-0.3.3.dist-info/RECORD
