Metadata-Version: 2.4
Name: e2xgrader
Version: 0.3.3
Summary: An addon for nbgrader
Project-URL: Source, https://github.com/Digiklausur/e2xgrader
Project-URL: Documentation, https://e2xgrader.readthedocs.io/en/latest/
Project-URL: Issues, https://github.com/Digiklausur/e2xgrader/issues
Project-URL: Pypi, https://pypi.org/project/e2xgrader/
Author-email: Tim Metzler <tim.metzler@h-brs.de>
License-Expression: MIT
License-File: LICENSE
Classifier: Programming Language :: Python
Classifier: Programming Language :: Python :: 3
Classifier: Programming Language :: Python :: 3.8
Classifier: Programming Language :: Python :: 3.9
Classifier: Programming Language :: Python :: 3.10
Classifier: Programming Language :: Python :: 3.11
Requires-Python: >=3.8
Requires-Dist: e2xauthoring<0.4,>=0.3.0
Requires-Dist: e2xcore>=0.0.5
Requires-Dist: pandas
Provides-Extra: dev
Requires-Dist: build; extra == 'dev'
Requires-Dist: hatchling; extra == 'dev'
Requires-Dist: pre-commit; extra == 'dev'
Requires-Dist: pytest-cov; extra == 'dev'
Requires-Dist: tbump; extra == 'dev'
Requires-Dist: twine; extra == 'dev'
